unsatfit/__init__.py
unsatfit/_contour.py
unsatfit/_cost.py
unsatfit/_figure.py
unsatfit/_init_bound.py
unsatfit/_init_fig.py
unsatfit/_init_lsq.py
unsatfit/_init_model.py
unsatfit/_model_bc.py
unsatfit/_model_bvv.py
unsatfit/_model_dual_bc.py
unsatfit/_model_dual_ko.py
unsatfit/_model_dual_vg.py
unsatfit/_model_fs.py
unsatfit/_model_fx.py
unsatfit/_model_k_vapor.py
unsatfit/_model_ko.py
unsatfit/_model_kobc.py
unsatfit/_model_modified.py
unsatfit/_model_pe.py
unsatfit/_model_tri_vg.py
unsatfit/_model_vg.py
unsatfit/_model_vgbc.py
unsatfit/_model_vvp.py
unsatfit/_optimize.py
unsatfit/_pore_size.py
unsatfit/_test.py
unsatfit/unsatfit.py
unsatfit-6.1.dist-info/licenses/LICENSE.txt
unsatfit-6.1.dist-info/METADATA
unsatfit-6.1.dist-info/WHEEL
unsatfit-6.1.dist-info/top_level.txt
unsatfit-6.1.dist-info/RECORD
